src/__init__.py
musico-0.0.2.dist-info/METADATA
musico-0.0.2.dist-info/WHEEL
musico-0.0.2.dist-info/licenses/LICENSE
musico-0.0.2.dist-info/RECORD
